{
    "(2886734945, 3741713926, 42242, 443, 'tcp', 0)": {
        "ts_list": [
            1645133604.260177,
            1645133604.260338,
            1645133604.260362,
            1645133604.288958,
            1645133604.288985,
            1645133604.289013,
            1645133604.289017,
            1645133604.289021,
            1645133604.289025,
            1645133604.28903,
            1645133604.289132,
            1645133604.289152,
            1645133604.289157,
            1645133604.289871,
            1645133604.289878,
            1645133604.289885,
            1645133604.289889,
            1645133604.357064,
            1645133604.52177,
            1645133604.521804,
            1645133604.549945,
            1645133604.549962,
            1645133604.549964,
            1645133604.549974,
            1645133604.550928,
            1645133604.550932,
            1645133604.550936,
            1645133604.550941,
            1645133604.678206,
            1645133604.67824,
            1645133604.706928,
            1645133604.706959,
            1645133604.706975,
            1645133604.707882,
            1645133604.707889,
            1645133604.70798,
            1645133604.707984,
            1645133604.953671,
            1645133604.953705,
            1645133604.961719,
            1645133604.961749,
            1645133604.981971,
            1645133604.98205,
            1645133604.982062,
            1645133604.983097,
            1645133604.983102,
            1645133604.983464,
            1645133604.983471,
            1645133604.989931,
            1645133604.98995,
            1645133604.989962,
            1645133604.990892,
            1645133604.990898,
            1645133604.990988,
            1645133604.990994,
            1645133604.994598,
            1645133604.994623,
            1645133605.023035,
            1645133605.023049,
            1645133605.0239,
            1645133605.023907,
            1645133605.023934,
            1645133605.028236,
            1645133605.028256,
            1645133605.056908,
            1645133605.056922,
            1645133605.057962,
            1645133605.057965,
            1645133605.058013,
            1645133605.058043,
            1645133605.085937,
            1645133605.085951,
            1645133605.087021,
            1645133605.087028,
            1645133605.087048,
            1645133605.470021,
            1645133605.470044,
            1645133605.497943,
            1645133605.497968,
            1645133605.498925,
            1645133605.498934,
            1645133605.498963
        ],
        "ps_list": [
            158,
            184,
            225,
            66,
            121,
            66,
            101,
            66,
            97,
            66,
            97,
            101,
            66,
            190,
            66,
            260,
            66,
            66,
            121,
            225,
            66,
            66,
            101,
            66,
            122,
            66,
            255,
            66,
            121,
            225,
            66,
            101,
            66,
            120,
            66,
            410,
            66,
            121,
            225,
            121,
            225,
            66,
            101,
            66,
            122,
            66,
            334,
            66,
            66,
            101,
            66,
            108,
            66,
            383,
            66,
            121,
            225,
            66,
            101,
            104,
            334,
            66,
            121,
            225,
            66,
            101,
            145,
            272,
            121,
            225,
            66,
            101,
            121,
            323,
            66,
            121,
            225,
            66,
            101,
            108,
            401,
            66
        ],
        "direction_list": [
            0,
            0,
            0,
            1,
            1,
            0,
            1,
            0,
            1,
            0,
            0,
            1,
            0,
            1,
            0,
            1,
            0,
            1,
            0,
            0,
            1,
            1,
            1,
            0,
            1,
            0,
            1,
            0,
            0,
            0,
            1,
            1,
            0,
            1,
            0,
            1,
            0,
            0,
            0,
            0,
            0,
            1,
            1,
            0,
            1,
            0,
            1,
            0,
            1,
            1,
            0,
            1,
            0,
            1,
            0,
            0,
            0,
            1,
            1,
            1,
            1,
            0,
            0,
            0,
            1,
            1,
            1,
            1,
            0,
            0,
            1,
            1,
            1,
            1,
            0,
            0,
            0,
            1,
            1,
            1,
            1,
            0
        ],
        "piat_list": [
            0.2918243408203125,
            0.16117095947265625,
            0.02384185791015625,
            28.596162796020508,
            0.026941299438476562,
            0.027894973754882812,
            0.0040531158447265625,
            0.0040531158447265625,
            0.0040531158447265625,
            0.0050067901611328125,
            0.10204315185546875,
            0.019788742065429688,
            0.0050067901611328125,
            0.7140636444091797,
            0.0069141387939453125,
            0.007152557373046875,
            0.0040531158447265625,
            67.17491149902344,
            164.70599174499512,
            0.03409385681152344,
            28.141021728515625,
            0.016927719116210938,
            0.0019073486328125,
            0.010013580322265625,
            0.9541511535644531,
            0.003814697265625,
            0.0040531158447265625,
            0.0050067901611328125,
            127.26497650146484,
            0.03409385681152344,
            28.68795394897461,
            0.030994415283203125,
            0.015974044799804688,
            0.9069442749023438,
            0.007152557373046875,
            0.09083747863769531,
            0.0040531158447265625,
            245.68700790405273,
            0.03409385681152344,
            8.01396369934082,
            0.030040740966796875,
            20.221948623657227,
            0.07891654968261719,
            0.012159347534179688,
            1.0349750518798828,
            0.0050067901611328125,
            0.3619194030761719,
            0.0069141387939453125,
            6.4601898193359375,
            0.018835067749023438,
            0.012159347534179688,
            0.9298324584960938,
            0.0059604644775390625,
            0.09012222290039062,
            0.0059604644775390625,
            3.6039352416992188,
            0.025033950805664062,
            28.4121036529541,
            0.014066696166992188,
            0.8509159088134766,
            0.0069141387939453125,
            0.026941299438476562,
            4.302024841308594,
            0.02002716064453125,
            28.651952743530273,
            0.014066696166992188,
            1.0399818420410156,
            0.0030994415283203125,
            0.04792213439941406,
            0.030040740966796875,
            27.894020080566406,
            0.014066696166992188,
            1.0700225830078125,
            0.0069141387939453125,
            0.02002716064453125,
            382.97295570373535,
            0.02288818359375,
            27.89902687072754,
            0.025033950805664062,
            0.9570121765136719,
            0.009059906005859375,
            0.029087066650390625
        ]
    }
}