{
    "(2886734945, 3741713926, 52732, 443, 'tcp', 0)": {
        "ts_list": [
            1645368202.476601,
            1645368202.476793,
            1645368202.476813,
            1645368202.502463,
            1645368202.502507,
            1645368202.502519,
            1645368202.502531,
            1645368202.502535,
            1645368202.502641,
            1645368202.502646,
            1645368202.502707,
            1645368202.503417,
            1645368202.503427,
            1645368202.503517,
            1645368202.503524,
            1645368202.568517,
            1645368202.768574,
            1645368202.768612,
            1645368202.794497,
            1645368202.794517,
            1645368202.794524,
            1645368202.794534,
            1645368202.795464,
            1645368202.795471,
            1645368202.79556,
            1645368202.795565,
            1645368202.860219,
            1645368202.860251,
            1645368202.862409,
            1645368202.862438,
            1645368202.885559,
            1645368202.88559,
            1645368202.885604,
            1645368202.886536,
            1645368202.886543,
            1645368202.88663,
            1645368202.886635,
            1645368202.888523,
            1645368202.888618,
            1645368202.888624,
            1645368202.889549,
            1645368202.889558,
            1645368202.889659,
            1645368202.889665,
            1645368204.20014,
            1645368204.200186,
            1645368204.21028,
            1645368204.210341,
            1645368204.225528,
            1645368204.225637,
            1645368204.225654,
            1645368204.226547,
            1645368204.226556,
            1645368204.226646,
            1645368204.22665,
            1645368204.23552,
            1645368204.235538,
            1645368204.235549,
            1645368204.236545,
            1645368204.236549,
            1645368204.236644,
            1645368204.236648,
            1645368204.305656,
            1645368204.305679,
            1645368204.3083,
            1645368204.308325,
            1645368204.322605,
            1645368204.32265,
            1645368204.331569,
            1645368204.331593,
            1645368204.331603,
            1645368204.332533,
            1645368204.33254,
            1645368204.33255,
            1645368204.332556,
            1645368204.333451,
            1645368204.333549,
            1645368204.333555,
            1645368204.334732,
            1645368204.334745,
            1645368204.33477,
            1645368204.348493,
            1645368204.348606,
            1645368204.349426,
            1645368204.349526,
            1645368204.349592
        ],
        "ps_list": [
            158,
            184,
            225,
            66,
            121,
            66,
            110,
            66,
            101,
            66,
            97,
            191,
            66,
            260,
            66,
            66,
            121,
            225,
            66,
            66,
            101,
            66,
            121,
            66,
            255,
            66,
            121,
            225,
            121,
            225,
            66,
            101,
            66,
            121,
            66,
            254,
            66,
            66,
            101,
            66,
            121,
            66,
            258,
            66,
            121,
            225,
            121,
            225,
            66,
            101,
            66,
            144,
            66,
            364,
            66,
            66,
            101,
            66,
            122,
            66,
            332,
            66,
            121,
            225,
            121,
            225,
            121,
            225,
            66,
            101,
            66,
            119,
            66,
            328,
            66,
            66,
            101,
            66,
            122,
            344,
            66,
            66,
            101,
            122,
            272,
            66
        ],
        "direction_list": [
            0,
            0,
            0,
            1,
            1,
            0,
            1,
            0,
            1,
            0,
            0,
            1,
            0,
            1,
            0,
            1,
            0,
            0,
            1,
            1,
            1,
            0,
            1,
            0,
            1,
            0,
            0,
            0,
            0,
            0,
            1,
            1,
            0,
            1,
            0,
            1,
            0,
            1,
            1,
            0,
            1,
            0,
            1,
            0,
            0,
            0,
            0,
            0,
            1,
            1,
            0,
            1,
            0,
            1,
            0,
            1,
            1,
            0,
            1,
            0,
            1,
            0,
            0,
            0,
            0,
            0,
            0,
            0,
            1,
            1,
            0,
            1,
            0,
            1,
            0,
            1,
            1,
            0,
            1,
            1,
            0,
            1,
            1,
            1,
            1,
            0
        ],
        "piat_list": [
            0.3159046173095703,
            0.19216537475585938,
            0.02002716064453125,
            25.6500244140625,
            0.0438690185546875,
            0.011920928955078125,
            0.012159347534179688,
            0.0040531158447265625,
            0.10585784912109375,
            0.0050067901611328125,
            0.06103515625,
            0.7100105285644531,
            0.010013580322265625,
            0.08988380432128906,
            0.007152557373046875,
            64.99290466308594,
            200.0570297241211,
            0.03790855407714844,
            25.88510513305664,
            0.02002716064453125,
            0.0069141387939453125,
            0.010013580322265625,
            0.9300708770751953,
            0.0069141387939453125,
            0.08893013000488281,
            0.0050067901611328125,
            64.65411186218262,
            0.031948089599609375,
            2.1581649780273438,
            0.028848648071289062,
            23.121118545532227,
            0.030994415283203125,
            0.013828277587890625,
            0.9319782257080078,
            0.007152557373046875,
            0.08702278137207031,
            0.0050067901611328125,
            1.8880367279052734,
            0.09489059448242188,
            0.0059604644775390625,
            0.9250640869140625,
            0.009059906005859375,
            0.10085105895996094,
            0.0059604644775390625,
            1310.4751110076904,
            0.04601478576660156,
            10.093927383422852,
            0.06103515625,
            15.18702507019043,
            0.10895729064941406,
            0.016927719116210938,
            0.8931159973144531,
            0.009059906005859375,
            0.08988380432128906,
            0.0040531158447265625,
            8.86988639831543,
            0.01811981201171875,
            0.010967254638671875,
            0.9961128234863281,
            0.003814697265625,
            0.09512901306152344,
            0.0040531158447265625,
            69.00787353515625,
            0.023126602172851562,
            2.6209354400634766,
            0.025033950805664062,
            14.279842376708984,
            0.04506111145019531,
            8.919000625610352,
            0.024080276489257812,
            0.010013580322265625,
            0.9298324584960938,
            0.007152557373046875,
            0.010013580322265625,
            0.0059604644775390625,
            0.8950233459472656,
            0.09799003601074219,
            0.0059604644775390625,
            1.177072525024414,
            0.012874603271484375,
            0.025033950805664062,
            13.723134994506836,
            0.11301040649414062,
            0.8199214935302734,
            0.09989738464355469,
            0.06604194641113281
        ]
    }
}