{
    "(2886734945, 3741648133, 43962, 443, 'tcp', 0)": {
        "ts_list": [
            1645591399.887971,
            1645591399.888239,
            1645591399.88826,
            1645591399.897297,
            1645591399.897329,
            1645591399.897344,
            1645591399.89737,
            1645591399.897376,
            1645591399.897379,
            1645591399.897383,
            1645591399.897493,
            1645591399.898219,
            1645591399.898234,
            1645591399.89825,
            1645591399.898256,
            1645591399.947358,
            1645591400.235128,
            1645591400.235167,
            1645591400.244154,
            1645591400.244183,
            1645591400.244323,
            1645591400.244336,
            1645591400.245231,
            1645591400.245235,
            1645591400.245329,
            1645591400.245333,
            1645591400.349065,
            1645591400.349096,
            1645591400.350659,
            1645591400.350698,
            1645591400.358166,
            1645591400.358253,
            1645591400.358263,
            1645591400.358275,
            1645591400.358279,
            1645591400.358286,
            1645591400.358289,
            1645591400.360119,
            1645591400.360212,
            1645591400.360219,
            1645591400.361227,
            1645591400.361232,
            1645591400.361324,
            1645591400.361329,
            1645591401.832436,
            1645591401.832483,
            1645591401.842185,
            1645591401.842263,
            1645591401.842275,
            1645591401.843192,
            1645591401.843198,
            1645591401.843291,
            1645591401.843294,
            1645591401.964486,
            1645591401.964533,
            1645591401.974205,
            1645591401.974289,
            1645591401.9743,
            1645591401.975181,
            1645591401.975186,
            1645591401.975278,
            1645591401.975282,
            1645591401.991662,
            1645591401.991695,
            1645591402.002184,
            1645591402.002249,
            1645591402.003192,
            1645591402.003286,
            1645591402.004098,
            1645591402.004574,
            1645591402.004597,
            1645591402.014244,
            1645591402.014323,
            1645591402.015154,
            1645591402.015187,
            1645591402.015252,
            1645591402.046006,
            1645591402.046031,
            1645591402.055251,
            1645591402.055326,
            1645591402.056143,
            1645591402.056176,
            1645591402.056241,
            1645591402.098788,
            1645591402.240566,
            1645591402.2406,
            1645591402.250168,
            1645591402.250272
        ],
        "ps_list": [
            158,
            184,
            225,
            66,
            121,
            66,
            110,
            66,
            101,
            66,
            97,
            191,
            66,
            260,
            66,
            66,
            121,
            225,
            66,
            66,
            101,
            66,
            144,
            66,
            255,
            66,
            121,
            225,
            121,
            225,
            66,
            101,
            66,
            121,
            66,
            252,
            66,
            66,
            101,
            66,
            121,
            66,
            312,
            66,
            121,
            225,
            66,
            101,
            66,
            144,
            66,
            272,
            66,
            121,
            225,
            66,
            101,
            66,
            120,
            66,
            401,
            66,
            121,
            225,
            66,
            101,
            122,
            310,
            66,
            121,
            225,
            66,
            101,
            122,
            66,
            276,
            121,
            225,
            66,
            101,
            145,
            66,
            345,
            66,
            121,
            225,
            66,
            101
        ],
        "direction_list": [
            0,
            0,
            0,
            1,
            1,
            0,
            1,
            0,
            1,
            0,
            0,
            1,
            0,
            1,
            0,
            1,
            0,
            0,
            1,
            1,
            1,
            0,
            1,
            0,
            1,
            0,
            0,
            0,
            0,
            0,
            1,
            1,
            0,
            1,
            0,
            1,
            0,
            1,
            1,
            0,
            1,
            0,
            1,
            0,
            0,
            0,
            1,
            1,
            0,
            1,
            0,
            1,
            0,
            0,
            0,
            1,
            1,
            0,
            1,
            0,
            1,
            0,
            0,
            0,
            1,
            1,
            1,
            1,
            0,
            0,
            0,
            1,
            1,
            1,
            0,
            1,
            0,
            0,
            1,
            1,
            1,
            0,
            1,
            0,
            0,
            0,
            1,
            1
        ],
        "piat_list": [
            0.26297569274902344,
            0.26798248291015625,
            0.0209808349609375,
            9.037017822265625,
            0.03218650817871094,
            0.015020370483398438,
            0.025987625122070312,
            0.0059604644775390625,
            0.00286102294921875,
            0.0040531158447265625,
            0.10991096496582031,
            0.7262229919433594,
            0.014781951904296875,
            0.01621246337890625,
            0.0059604644775390625,
            49.101829528808594,
            287.77003288269043,
            0.03910064697265625,
            8.986949920654297,
            0.029087066650390625,
            0.1399517059326172,
            0.012874603271484375,
            0.8950233459472656,
            0.0040531158447265625,
            0.09393692016601562,
            0.0040531158447265625,
            103.73210906982422,
            0.030994415283203125,
            1.5628337860107422,
            0.03910064697265625,
            7.467985153198242,
            0.08702278137207031,
            0.010013580322265625,
            0.011920928955078125,
            0.0040531158447265625,
            0.0069141387939453125,
            0.0030994415283203125,
            1.8301010131835938,
            0.09298324584960938,
            0.0069141387939453125,
            1.0080337524414062,
            0.0050067901611328125,
            0.09202957153320312,
            0.0050067901611328125,
            1471.107006072998,
            0.04696846008300781,
            9.701967239379883,
            0.07796287536621094,
            0.011920928955078125,
            0.9171962738037109,
            0.0059604644775390625,
            0.09298324584960938,
            0.00286102294921875,
            121.19197845458984,
            0.047206878662109375,
            9.671926498413086,
            0.08392333984375,
            0.010967254638671875,
            0.881195068359375,
            0.0050067901611328125,
            0.09179115295410156,
            0.0040531158447265625,
            16.38007164001465,
            0.032901763916015625,
            10.48898696899414,
            0.06508827209472656,
            0.9429454803466797,
            0.09393692016601562,
            0.8120536804199219,
            0.4761219024658203,
            0.02288818359375,
            9.647130966186523,
            0.07891654968261719,
            0.8308887481689453,
            0.03314018249511719,
            0.06508827209472656,
            30.75385093688965,
            0.025033950805664062,
            9.219884872436523,
            0.07510185241699219,
            0.8170604705810547,
            0.032901763916015625,
            0.06508827209472656,
            42.546987533569336,
            141.77799224853516,
            0.03409385681152344,
            9.567975997924805,
            0.10395050048828125
        ]
    }
}