{
    "(2886734945, 3741713926, 53380, 443, 'tcp', 0)": {
        "ts_list": [
            1645168828.28566,
            1645168828.285835,
            1645168828.285854,
            1645168828.31357,
            1645168828.313608,
            1645168828.313761,
            1645168828.314536,
            1645168828.314638,
            1645168828.314648,
            1645168828.314654,
            1645168828.314659,
            1645168828.314661,
            1645168828.314665,
            1645168828.315524,
            1645168828.315534,
            1645168828.315621,
            1645168828.315625,
            1645168828.382776,
            1645168828.569953,
            1645168828.569998,
            1645168828.598626,
            1645168828.598656,
            1645168828.598675,
            1645168828.598688,
            1645168828.599662,
            1645168828.599666,
            1645168828.59976,
            1645168828.599765,
            1645168828.68245,
            1645168828.682482,
            1645168828.710601,
            1645168828.710676,
            1645168828.710687,
            1645168828.71166,
            1645168828.711664,
            1645168828.711759,
            1645168828.711763,
            1645168828.900688,
            1645168828.900726,
            1645168828.929657,
            1645168828.929689,
            1645168828.929704,
            1645168828.930662,
            1645168828.930671,
            1645168828.930756,
            1645168828.93077,
            1645168829.661989,
            1645168829.662031,
            1645168829.69067,
            1645168829.690701,
            1645168829.690712,
            1645168829.691633,
            1645168829.691638,
            1645168829.691732,
            1645168829.691736,
            1645168829.767732,
            1645168829.767757,
            1645168829.796684,
            1645168829.796708,
            1645168829.796718,
            1645168829.797597,
            1645168829.797602,
            1645168829.797608,
            1645168829.797612,
            1645168829.878215,
            1645168829.878249,
            1645168829.906619,
            1645168829.906795,
            1645168829.906814,
            1645168829.907681,
            1645168829.907692,
            1645168829.907776,
            1645168829.90778,
            1645168829.921679,
            1645168829.921703,
            1645168829.950787,
            1645168829.950807,
            1645168829.951685,
            1645168829.951716,
            1645168829.951867,
            1645168829.968781,
            1645168829.968804,
            1645168829.997789,
            1645168829.997873,
            1645168829.999153,
            1645168829.999196,
            1645168830.000326,
            1645168830.046783
        ],
        "ps_list": [
            158,
            184,
            225,
            121,
            66,
            97,
            66,
            101,
            66,
            97,
            66,
            101,
            66,
            191,
            66,
            260,
            66,
            66,
            121,
            225,
            66,
            66,
            101,
            66,
            121,
            66,
            255,
            66,
            121,
            225,
            66,
            101,
            66,
            122,
            66,
            250,
            66,
            121,
            225,
            66,
            101,
            66,
            120,
            66,
            502,
            66,
            121,
            225,
            66,
            101,
            66,
            143,
            66,
            298,
            66,
            121,
            225,
            66,
            101,
            66,
            121,
            66,
            394,
            66,
            121,
            225,
            66,
            101,
            66,
            120,
            66,
            297,
            66,
            121,
            225,
            66,
            101,
            122,
            66,
            272,
            121,
            225,
            66,
            101,
            121,
            66,
            332,
            66
        ],
        "direction_list": [
            0,
            0,
            0,
            1,
            0,
            0,
            1,
            1,
            0,
            1,
            0,
            1,
            0,
            1,
            0,
            1,
            0,
            1,
            0,
            0,
            1,
            1,
            1,
            0,
            1,
            0,
            1,
            0,
            0,
            0,
            1,
            1,
            0,
            1,
            0,
            1,
            0,
            0,
            0,
            1,
            1,
            0,
            1,
            0,
            1,
            0,
            0,
            0,
            1,
            1,
            0,
            1,
            0,
            1,
            0,
            0,
            0,
            1,
            1,
            0,
            1,
            0,
            1,
            0,
            0,
            0,
            1,
            1,
            0,
            1,
            0,
            1,
            0,
            0,
            0,
            1,
            1,
            1,
            0,
            1,
            0,
            0,
            1,
            1,
            1,
            0,
            1,
            0
        ],
        "piat_list": [
            0.2961158752441406,
            0.17499923706054688,
            0.019073486328125,
            27.71592140197754,
            0.03790855407714844,
            0.15306472778320312,
            0.7750988006591797,
            0.10180473327636719,
            0.010013580322265625,
            0.006198883056640625,
            0.0050067901611328125,
            0.0019073486328125,
            0.0040531158447265625,
            0.8590221405029297,
            0.010013580322265625,
            0.08678436279296875,
            0.0040531158447265625,
            67.15106964111328,
            187.17694282531738,
            0.04506111145019531,
            28.627872467041016,
            0.030040740966796875,
            0.019073486328125,
            0.012874603271484375,
            0.9741783142089844,
            0.0040531158447265625,
            0.09393692016601562,
            0.0050067901611328125,
            82.68499374389648,
            0.031948089599609375,
            28.11908721923828,
            0.07486343383789062,
            0.010967254638671875,
            0.9729862213134766,
            0.0040531158447265625,
            0.09512901306152344,
            0.003814697265625,
            188.92502784729004,
            0.03814697265625,
            28.9309024810791,
            0.031948089599609375,
            0.015020370483398438,
            0.9579658508300781,
            0.009059906005859375,
            0.08511543273925781,
            0.013828277587890625,
            731.2190532684326,
            0.041961669921875,
            28.63907814025879,
            0.030994415283203125,
            0.010967254638671875,
            0.9210109710693359,
            0.0050067901611328125,
            0.09393692016601562,
            0.0040531158447265625,
            75.99592208862305,
            0.025033950805664062,
            28.927087783813477,
            0.024080276489257812,
            0.009775161743164062,
            0.8790493011474609,
            0.0050067901611328125,
            0.0059604644775390625,
            0.0040531158447265625,
            80.60312271118164,
            0.033855438232421875,
            28.370141983032227,
            0.17595291137695312,
            0.019073486328125,
            0.8668899536132812,
            0.010967254638671875,
            0.08416175842285156,
            0.003814697265625,
            13.899087905883789,
            0.024080276489257812,
            29.083967208862305,
            0.02002716064453125,
            0.8778572082519531,
            0.030994415283203125,
            0.15115737915039062,
            16.913890838623047,
            0.02288818359375,
            28.985023498535156,
            0.08416175842285156,
            1.2798309326171875,
            0.04315376281738281,
            1.1298656463623047,
            46.45705223083496
        ]
    }
}