{
    "(2886734945, 3741713926, 50330, 443, 'tcp', 0)": {
        "ts_list": [
            1644919301.825175,
            1644919301.825357,
            1644919301.825375,
            1644919301.85362,
            1644919301.853652,
            1644919301.853664,
            1644919301.8537,
            1644919301.853705,
            1644919301.853797,
            1644919301.8546,
            1644919301.854698,
            1644919301.854702,
            1644919301.855618,
            1644919301.855623,
            1644919301.855716,
            1644919301.85572,
            1644919301.922677,
            1644919302.056417,
            1644919302.056454,
            1644919302.085625,
            1644919302.085649,
            1644919302.085652,
            1644919302.085663,
            1644919302.086612,
            1644919302.086617,
            1644919302.086711,
            1644919302.086818,
            1644919302.148123,
            1644919302.148152,
            1644919302.176652,
            1644919302.176681,
            1644919302.176769,
            1644919302.177685,
            1644919302.177721,
            1644919302.17778,
            1644919302.177844,
            1644919302.49372,
            1644919302.493758,
            1644919302.522882,
            1644919302.523243,
            1644919302.523258,
            1644919302.541644,
            1644919302.541673,
            1644919302.541687,
            1644919302.541692,
            1644919302.611397,
            1644919302.611422,
            1644919302.640655,
            1644919302.640677,
            1644919302.640686,
            1644919302.641605,
            1644919302.641611,
            1644919302.641618,
            1644919302.641623,
            1644919302.715961,
            1644919302.715984,
            1644919302.744642,
            1644919302.744686,
            1644919302.744694,
            1644919302.745667,
            1644919302.745671,
            1644919302.745789,
            1644919302.745792,
            1644919302.784107,
            1644919302.784131,
            1644919302.812613,
            1644919302.812709,
            1644919302.812716,
            1644919302.813637,
            1644919302.813644,
            1644919302.813664,
            1644919302.870253,
            1644919302.870277,
            1644919302.898651,
            1644919302.898667,
            1644919302.898714,
            1644919302.899676,
            1644919302.899699,
            1644919302.899774,
            1644919302.899785
        ],
        "ps_list": [
            158,
            184,
            225,
            66,
            121,
            66,
            110,
            66,
            97,
            66,
            101,
            66,
            190,
            66,
            260,
            66,
            66,
            121,
            225,
            66,
            66,
            101,
            66,
            144,
            66,
            255,
            66,
            121,
            225,
            66,
            101,
            66,
            121,
            66,
            287,
            66,
            121,
            225,
            66,
            101,
            66,
            123,
            66,
            253,
            66,
            121,
            225,
            66,
            101,
            66,
            121,
            66,
            298,
            66,
            121,
            225,
            66,
            101,
            66,
            121,
            66,
            297,
            66,
            121,
            225,
            66,
            101,
            66,
            121,
            272,
            66,
            121,
            225,
            66,
            101,
            66,
            121,
            66,
            309,
            66
        ],
        "direction_list": [
            0,
            0,
            0,
            1,
            1,
            0,
            1,
            0,
            0,
            1,
            1,
            0,
            1,
            0,
            1,
            0,
            1,
            0,
            0,
            1,
            1,
            1,
            0,
            1,
            0,
            1,
            0,
            0,
            0,
            1,
            1,
            0,
            1,
            0,
            1,
            0,
            0,
            0,
            1,
            1,
            0,
            1,
            0,
            1,
            0,
            0,
            0,
            1,
            1,
            0,
            1,
            0,
            1,
            0,
            0,
            0,
            1,
            1,
            0,
            1,
            0,
            1,
            0,
            0,
            0,
            1,
            1,
            0,
            1,
            1,
            0,
            0,
            0,
            1,
            1,
            0,
            1,
            0,
            1,
            0
        ],
        "piat_list": [
            0.2651214599609375,
            0.1819133758544922,
            0.01811981201171875,
            28.244972229003906,
            0.031948089599609375,
            0.011920928955078125,
            0.03600120544433594,
            0.0050067901611328125,
            0.09202957153320312,
            0.8029937744140625,
            0.09799003601074219,
            0.0040531158447265625,
            0.9160041809082031,
            0.0050067901611328125,
            0.09298324584960938,
            0.0040531158447265625,
            66.95699691772461,
            133.73994827270508,
            0.03695487976074219,
            29.170989990234375,
            0.024080276489257812,
            0.0030994415283203125,
            0.010967254638671875,
            0.9489059448242188,
            0.0050067901611328125,
            0.09393692016601562,
            0.10704994201660156,
            61.30504608154297,
            0.029087066650390625,
            28.499841690063477,
            0.029087066650390625,
            0.08797645568847656,
            0.9160041809082031,
            0.03600120544433594,
            0.05888938903808594,
            0.06413459777832031,
            315.8760070800781,
            0.03790855407714844,
            29.124021530151367,
            0.3609657287597656,
            0.015020370483398438,
            18.386125564575195,
            0.028848648071289062,
            0.014066696166992188,
            0.0050067901611328125,
            69.70500946044922,
            0.025033950805664062,
            29.23297882080078,
            0.02193450927734375,
            0.009059906005859375,
            0.9188652038574219,
            0.006198883056640625,
            0.0069141387939453125,
            0.0050067901611328125,
            74.33795928955078,
            0.023126602172851562,
            28.657913208007812,
            0.0438690185546875,
            0.008106231689453125,
            0.9729862213134766,
            0.0040531158447265625,
            0.11801719665527344,
            0.00286102294921875,
            38.3150577545166,
            0.024080276489257812,
            28.48196029663086,
            0.09608268737792969,
            0.0069141387939453125,
            0.9210109710693359,
            0.0069141387939453125,
            0.02002716064453125,
            56.58912658691406,
            0.02384185791015625,
            28.37395668029785,
            0.01621246337890625,
            0.04696846008300781,
            0.9620189666748047,
            0.02288818359375,
            0.07510185241699219,
            0.010967254638671875
        ]
    }
}