{
    "(2886734945, 3741713926, 47578, 443, 'tcp', 0)": {
        "ts_list": [
            1645642311.805953,
            1645642311.806126,
            1645642311.806151,
            1645642311.832432,
            1645642311.832464,
            1645642311.832479,
            1645642311.832501,
            1645642311.832507,
            1645642311.83251,
            1645642311.83266,
            1645642311.832792,
            1645642311.832797,
            1645642311.832803,
            1645642311.832807,
            1645642311.832891,
            1645642311.832896,
            1645642311.898518,
            1645642312.146931,
            1645642312.146971,
            1645642312.173343,
            1645642312.173368,
            1645642312.173409,
            1645642312.173423,
            1645642312.173511,
            1645642312.173515,
            1645642312.173518,
            1645642312.173522,
            1645642312.223848,
            1645642312.223886,
            1645642312.227552,
            1645642312.227589,
            1645642312.250318,
            1645642312.250348,
            1645642312.250364,
            1645642312.250378,
            1645642312.250381,
            1645642312.25039,
            1645642312.250393,
            1645642312.253946,
            1645642312.254035,
            1645642312.254043,
            1645642312.254138,
            1645642312.254142,
            1645642312.25415,
            1645642312.254154,
            1645642312.406783,
            1645642312.406817,
            1645642312.433218,
            1645642312.433255,
            1645642312.433269,
            1645642312.433282,
            1645642312.433363,
            1645642312.433389,
            1645642312.433508,
            1645642312.471798,
            1645642312.471827,
            1645642312.498224,
            1645642312.498288,
            1645642312.498372,
            1645642312.498399,
            1645642312.498401,
            1645642312.498415,
            1645642312.652273,
            1645642312.652314,
            1645642312.67422,
            1645642312.674256,
            1645642312.678846,
            1645642312.678865,
            1645642312.678872,
            1645642312.678875,
            1645642312.678918,
            1645642312.696867,
            1645642312.696897,
            1645642312.700705,
            1645642312.700723,
            1645642312.70073,
            1645642312.700783,
            1645642312.700796,
            1645642312.72328,
            1645642312.72331,
            1645642312.723356,
            1645642312.723359,
            1645642312.72338,
            1645642312.770793
        ],
        "ps_list": [
            164,
            184,
            225,
            66,
            121,
            66,
            110,
            66,
            66,
            97,
            101,
            66,
            191,
            66,
            260,
            66,
            66,
            121,
            225,
            66,
            66,
            101,
            66,
            144,
            66,
            255,
            66,
            121,
            225,
            121,
            225,
            66,
            101,
            66,
            119,
            66,
            247,
            66,
            66,
            101,
            66,
            107,
            66,
            311,
            66,
            121,
            225,
            66,
            101,
            66,
            107,
            66,
            314,
            66,
            121,
            225,
            66,
            101,
            66,
            121,
            363,
            66,
            121,
            225,
            121,
            225,
            66,
            101,
            121,
            366,
            66,
            121,
            225,
            66,
            101,
            117,
            366,
            66,
            66,
            101,
            121,
            344,
            66,
            66
        ],
        "direction_list": [
            0,
            0,
            0,
            1,
            1,
            0,
            1,
            0,
            1,
            0,
            1,
            0,
            1,
            0,
            1,
            0,
            1,
            0,
            0,
            1,
            1,
            1,
            0,
            1,
            0,
            1,
            0,
            0,
            0,
            0,
            0,
            1,
            1,
            0,
            1,
            0,
            1,
            0,
            1,
            1,
            0,
            1,
            0,
            1,
            0,
            0,
            0,
            1,
            1,
            0,
            1,
            0,
            1,
            0,
            0,
            0,
            1,
            1,
            0,
            1,
            1,
            0,
            0,
            0,
            0,
            0,
            1,
            1,
            1,
            1,
            0,
            0,
            0,
            1,
            1,
            1,
            1,
            0,
            1,
            1,
            1,
            1,
            0,
            0
        ],
        "piat_list": [
            0.3139972686767578,
            0.17309188842773438,
            0.0247955322265625,
            26.281118392944336,
            0.031948089599609375,
            0.015020370483398438,
            0.02193450927734375,
            0.0059604644775390625,
            0.0030994415283203125,
            0.1499652862548828,
            0.13208389282226562,
            0.0050067901611328125,
            0.0059604644775390625,
            0.0040531158447265625,
            0.08392333984375,
            0.0050067901611328125,
            65.62209129333496,
            248.4128475189209,
            0.0400543212890625,
            26.37195587158203,
            0.025033950805664062,
            0.04100799560546875,
            0.014066696166992188,
            0.08797645568847656,
            0.0040531158447265625,
            0.00286102294921875,
            0.0040531158447265625,
            50.32610893249512,
            0.03790855407714844,
            3.665924072265625,
            0.03695487976074219,
            22.729158401489258,
            0.030040740966796875,
            0.015974044799804688,
            0.013828277587890625,
            0.0030994415283203125,
            0.009059906005859375,
            0.00286102294921875,
            3.553152084350586,
            0.08893013000488281,
            0.008106231689453125,
            0.09489059448242188,
            0.0040531158447265625,
            0.007867813110351562,
            0.0040531158447265625,
            152.62913703918457,
            0.033855438232421875,
            26.401042938232422,
            0.03695487976074219,
            0.014066696166992188,
            0.012874603271484375,
            0.08106231689453125,
            0.025987625122070312,
            0.11897087097167969,
            38.29002380371094,
            0.029087066650390625,
            26.396989822387695,
            0.06389617919921875,
            0.08416175842285156,
            0.026941299438476562,
            0.0019073486328125,
            0.014066696166992188,
            153.85794639587402,
            0.04100799560546875,
            21.906137466430664,
            0.03600120544433594,
            4.58979606628418,
            0.019073486328125,
            0.007152557373046875,
            0.00286102294921875,
            0.04291534423828125,
            17.94910430908203,
            0.030040740966796875,
            3.8080215454101562,
            0.017881393432617188,
            0.007152557373046875,
            0.052928924560546875,
            0.012874603271484375,
            22.48406410217285,
            0.030040740966796875,
            0.04601478576660156,
            0.0030994415283203125,
            0.0209808349609375,
            47.412872314453125
        ]
    }
}