{
    "(2886734945, 3741648133, 33182, 443, 'tcp', 0)": {
        "ts_list": [
            1645123667.337934,
            1645123667.338117,
            1645123667.338141,
            1645123667.348118,
            1645123667.348159,
            1645123667.348173,
            1645123667.34818,
            1645123667.348185,
            1645123667.348193,
            1645123667.348197,
            1645123667.349176,
            1645123667.349185,
            1645123667.349188,
            1645123667.349193,
            1645123667.352669,
            1645123667.402162,
            1645123667.633213,
            1645123667.633253,
            1645123667.643046,
            1645123667.643076,
            1645123667.643255,
            1645123667.643272,
            1645123667.644116,
            1645123667.644128,
            1645123667.644264,
            1645123667.644274,
            1645123667.749528,
            1645123667.749555,
            1645123667.750997,
            1645123667.751024,
            1645123667.759083,
            1645123667.759204,
            1645123667.759214,
            1645123667.760096,
            1645123667.760103,
            1645123667.760111,
            1645123667.760116,
            1645123667.761144,
            1645123667.761238,
            1645123667.761244,
            1645123667.762113,
            1645123667.76212,
            1645123667.762125,
            1645123667.76213,
            1645123668.262064,
            1645123668.2621,
            1645123668.263447,
            1645123668.263475,
            1645123668.27211,
            1645123668.272189,
            1645123668.272203,
            1645123668.273086,
            1645123668.273185,
            1645123668.273191,
            1645123668.273287,
            1645123668.273292,
            1645123668.273294,
            1645123668.273298,
            1645123668.274164,
            1645123668.27417,
            1645123668.274177,
            1645123668.274181,
            1645123668.312664,
            1645123668.312698,
            1645123668.322107,
            1645123668.322195,
            1645123668.322204,
            1645123668.323191,
            1645123668.323199,
            1645123668.323207,
            1645123668.323212,
            1645123668.391374,
            1645123668.391403,
            1645123668.401159,
            1645123668.401261,
            1645123668.401275,
            1645123668.402219,
            1645123668.402232,
            1645123668.402244,
            1645123668.402249,
            1645123668.475789,
            1645123668.475823,
            1645123668.485052,
            1645123668.485158,
            1645123668.486092,
            1645123668.486189,
            1645123668.489444
        ],
        "ps_list": [
            158,
            184,
            225,
            66,
            121,
            66,
            110,
            66,
            101,
            66,
            191,
            66,
            260,
            66,
            97,
            66,
            121,
            225,
            66,
            66,
            101,
            66,
            121,
            66,
            255,
            66,
            121,
            225,
            121,
            225,
            66,
            101,
            66,
            121,
            66,
            252,
            66,
            66,
            101,
            66,
            121,
            66,
            415,
            66,
            121,
            225,
            121,
            225,
            66,
            101,
            66,
            66,
            143,
            66,
            297,
            66,
            101,
            66,
            121,
            66,
            423,
            66,
            121,
            225,
            66,
            101,
            66,
            122,
            66,
            272,
            66,
            121,
            225,
            66,
            101,
            66,
            121,
            66,
            257,
            66,
            121,
            225,
            66,
            101,
            122,
            264,
            66
        ],
        "direction_list": [
            0,
            0,
            0,
            1,
            1,
            0,
            1,
            0,
            1,
            0,
            1,
            0,
            1,
            0,
            0,
            1,
            0,
            0,
            1,
            1,
            1,
            0,
            1,
            0,
            1,
            0,
            0,
            0,
            0,
            0,
            1,
            1,
            0,
            1,
            0,
            1,
            0,
            1,
            1,
            0,
            1,
            0,
            1,
            0,
            0,
            0,
            0,
            0,
            1,
            1,
            0,
            1,
            1,
            0,
            1,
            0,
            1,
            0,
            1,
            0,
            1,
            0,
            0,
            0,
            1,
            1,
            0,
            1,
            0,
            1,
            0,
            0,
            0,
            1,
            1,
            0,
            1,
            0,
            1,
            0,
            0,
            0,
            1,
            1,
            1,
            1,
            0
        ],
        "piat_list": [
            0.26297569274902344,
            0.18286705017089844,
            0.024080276489257812,
            9.977102279663086,
            0.04100799560546875,
            0.013828277587890625,
            0.007152557373046875,
            0.0050067901611328125,
            0.007867813110351562,
            0.0040531158447265625,
            0.9789466857910156,
            0.009059906005859375,
            0.0030994415283203125,
            0.0050067901611328125,
            3.4759044647216797,
            49.49307441711426,
            231.05096817016602,
            0.0400543212890625,
            9.792804718017578,
            0.030040740966796875,
            0.17905235290527344,
            0.016927719116210938,
            0.8440017700195312,
            0.012159347534179688,
            0.13589859008789062,
            0.010013580322265625,
            105.25393486022949,
            0.027179718017578125,
            1.44195556640625,
            0.026941299438476562,
            8.059024810791016,
            0.12087821960449219,
            0.010013580322265625,
            0.8821487426757812,
            0.0069141387939453125,
            0.008106231689453125,
            0.0050067901611328125,
            1.027822494506836,
            0.09417533874511719,
            0.0059604644775390625,
            0.8690357208251953,
            0.0069141387939453125,
            0.0050067901611328125,
            0.0050067901611328125,
            499.93395805358887,
            0.03600120544433594,
            1.3470649719238281,
            0.027894973754882812,
            8.63504409790039,
            0.07891654968261719,
            0.014066696166992188,
            0.8831024169921875,
            0.09894371032714844,
            0.0059604644775390625,
            0.09608268737792969,
            0.0050067901611328125,
            0.0019073486328125,
            0.0040531158447265625,
            0.865936279296875,
            0.0059604644775390625,
            0.007152557373046875,
            0.003814697265625,
            38.4831428527832,
            0.033855438232421875,
            9.409189224243164,
            0.08797645568847656,
            0.009059906005859375,
            0.9868144989013672,
            0.008106231689453125,
            0.007867813110351562,
            0.0050067901611328125,
            68.16220283508301,
            0.028848648071289062,
            9.756088256835938,
            0.10204315185546875,
            0.013828277587890625,
            0.9441375732421875,
            0.012874603271484375,
            0.012159347534179688,
            0.0050067901611328125,
            73.53997230529785,
            0.033855438232421875,
            9.229183197021484,
            0.10585784912109375,
            0.9341239929199219,
            0.09679794311523438,
            3.255128860473633
        ]
    }
}